envguard/__init__.py
envguard/__main__.py
envguard/cli.py
envguard/compose.py
envguard/dotenv.py
envguard/report.py
envguard/scanner.py
dotenvcheck-0.1.9.dist-info/METADATA
dotenvcheck-0.1.9.dist-info/WHEEL
dotenvcheck-0.1.9.dist-info/entry_points.txt
dotenvcheck-0.1.9.dist-info/licenses/LICENSE
dotenvcheck-0.1.9.dist-info/RECORD
