Metadata-Version: 2.4
Name: dotenvcheck
Version: 0.1.9
Summary: Cross-check environment variables used in Python code against .env and docker-compose.
Author-email: Dipendra Pant <dipendrapant778@gmail.com>
License-Expression: MIT
License-File: LICENSE
Keywords: ci,devops,dotenv,env,linter
Classifier: Environment :: Console
Classifier: License :: OSI Approved :: MIT License
Classifier: Programming Language :: Python :: 3
Classifier: Topic :: Software Development :: Quality Assurance
Classifier: Topic :: Utilities
Requires-Python: >=3.8
Requires-Dist: tomli>=2.0.1; python_version < '3.11'
Provides-Extra: compose
Requires-Dist: pyyaml>=6.0.1; extra == 'compose'
